excentis/xra31/__init__.py
excentis/xra31/analysis.py
excentis/xra31/capture.py
excentis/xra31/client.py
excentis/xra31/configuration.py
excentis/xra31/core.py
excentis/xra31/decorate.py
excentis/xra31/exceptions.py
excentis/xra31/trace.py
excentis/xra31/version.py
excentis/xra31/cli/__init__.py
excentis/xra31/cli/xra31_analyse.py
excentis/xra31/cli/xra31_capture.py
excentis/xra31/cli/xra31_configure.py
excentis_xra31-5.3.0.dist-info/LICENSE.txt
excentis_xra31-5.3.0.dist-info/METADATA
excentis_xra31-5.3.0.dist-info/WHEEL
excentis_xra31-5.3.0.dist-info/entry_points.txt
excentis_xra31-5.3.0.dist-info/top_level.txt
excentis_xra31-5.3.0.dist-info/RECORD
