Metadata-Version: 2.1
Name: excentis-xra31
Version: 5.3.0
Summary: XRA-31 Python and Command-line Interface
Home-page: https://www.xra31.com
Author: Excentis XRA-31 Development Team
Author-email: support.xra31@excentis.com
License: BSD-3-Clause
Project-URL: Documentation, https://python.xra31.com
Keywords: excentis xra-31
Classifier: Programming Language :: Python :: 3
Classifier: Operating System :: OS Independent
Classifier: License :: OSI Approved :: BSD License
Requires-Python: >=3.5,<4
License-File: LICENSE.txt
Requires-Dist: requests (<3.0.0,>=2.24.0)
Requires-Dist: importlib-metadata (>=1.7.0) ; python_version < "3.8"
